flask_header_log_request_id/__init__.py
flask_header_log_request_id/log_filter.py
flask_header_log_request_id/request_id.py
flask_header_log_request_id-0.1.0.dist-info/LICENSE
flask_header_log_request_id-0.1.0.dist-info/METADATA
flask_header_log_request_id-0.1.0.dist-info/WHEEL
flask_header_log_request_id-0.1.0.dist-info/top_level.txt
flask_header_log_request_id-0.1.0.dist-info/RECORD
