Metadata-Version: 2.1
Name: flask_header_log_request_id
Version: 0.1.0
Summary: Python Flask Middleware to log and set Request ID in the HTTP header
Home-page: https://github.com/Shatrugna-Strife/flask-header-log-request-id
Author: Shatru
Author-email: shatrugnakorukanti@gmail.com
License: MIT
Classifier: Development Status :: 3 - Alpha
Classifier: Framework :: Flask
Classifier: Intended Audience :: Developers
Classifier: Operating System :: OS Independent
Classifier: Programming Language :: Python :: 3
Classifier: Topic :: Software Development :: Libraries :: Python Modules
License-File: LICENSE
Requires-Dist: Flask
